brainmass/__init__.py
brainmass/_xy_model.py
brainmass/coupling.py
brainmass/coupling_test.py
brainmass/fhn.py
brainmass/fhn_test.py
brainmass/forward_model.py
brainmass/forward_model_test.py
brainmass/hopf.py
brainmass/hopf_test.py
brainmass/horn.py
brainmass/jansen_rit.py
brainmass/jansen_rit_test.py
brainmass/kuramoto.py
brainmass/leadfield.py
brainmass/linear.py
brainmass/linear_test.py
brainmass/noise.py
brainmass/noise_test.py
brainmass/qif.py
brainmass/qif_test.py
brainmass/sl.py
brainmass/sl_test.py
brainmass/typing.py
brainmass/utils.py
brainmass/vdp.py
brainmass/vdp_test.py
brainmass/wilson_cowan.py
brainmass/wilson_cowan_test.py
brainmass/wong_wang.py
brainmass/wong_wang_test.py
brainmass-0.0.5.dist-info/licenses/LICENSE
brainmass-0.0.5.dist-info/METADATA
brainmass-0.0.5.dist-info/WHEEL
brainmass-0.0.5.dist-info/top_level.txt
brainmass-0.0.5.dist-info/RECORD
