Metadata-Version: 2.4
Name: brainmass
Version: 0.0.5
Summary: Whole-brain brain modeling for differentiable neural mass models.
Author-email: BranMass Developers <chao.brain@qq.com>
Project-URL: homepage, https://github.com/chaobrain/brainmass
Project-URL: repository, https://github.com/chaobrain/brainmass
Project-URL: documentation, https://brainmass.readthedocs.io/
Project-URL: Bug Tracker, https://github.com/chaobrain/brainmass/issues
Project-URL: Source Code, https://github.com/chaobrain/brainmass
Keywords: neural mass model,brain modeling,rate model,mean field model,neuroscience,computational neuroscience,brain simulation
Classifier: Natural Language :: English
Classifier: Operating System :: OS Independent
Classifier: Development Status :: 4 - Beta
Classifier: Intended Audience :: Developers
Classifier: Intended Audience :: Science/Research
Classifier: Programming Language :: Python
Classifier: Programming Language :: Python :: 3
Classifier: Programming Language :: Python :: 3.10
Classifier: Programming Language :: Python :: 3.11
Classifier: Programming Language :: Python :: 3.12
Classifier: Programming Language :: Python :: 3.13
Classifier: Programming Language :: Python :: 3.14
Classifier: Topic :: Scientific/Engineering :: Bio-Informatics
Classifier: Topic :: Scientific/Engineering :: Mathematics
Classifier: Topic :: Scientific/Engineering :: Artificial Intelligence
Classifier: Topic :: Software Development :: Libraries
Requires-Python: >=3.10
License-File: LICENSE
Requires-Dist: numpy
Requires-Dist: jax
Requires-Dist: brainstate>=0.2.9
Requires-Dist: brainunit
Requires-Dist: braintools
Provides-Extra: testing
Requires-Dist: pytest; extra == "testing"
Provides-Extra: cpu
Requires-Dist: jax; extra == "cpu"
Provides-Extra: cuda12
Requires-Dist: jax[cuda12]; extra == "cuda12"
Provides-Extra: cuda13
Requires-Dist: jax[cuda13]; extra == "cuda13"
Provides-Extra: tpu
Requires-Dist: jax[tpu]; extra == "tpu"
Dynamic: license-file
